panopto_client/VERSION
panopto_client/__init__.py
panopto_client/access.py
panopto_client/remote_recorder.py
panopto_client/session.py
panopto_client/test.py
panopto_client/usage.py
panopto_client/user.py
panopto_client/mock_data/__init__.py
panopto_client/mock_data/data/README
panopto_client/tests/__init__.py
panopto_client/tests/test_access.py
panopto_client/tests/test_client.py
panopto_client/tests/test_remote_recorder.py
panopto_client/tests/test_session.py
panopto_client/tests/test_usage.py
panopto_client/tests/test_user.py
UW_Panopto_Client-0.3.5.dist-info/LICENSE
UW_Panopto_Client-0.3.5.dist-info/METADATA
UW_Panopto_Client-0.3.5.dist-info/WHEEL
UW_Panopto_Client-0.3.5.dist-info/top_level.txt
UW_Panopto_Client-0.3.5.dist-info/RECORD
