Metadata-Version: 2.1
Name: UW-Panopto-Client
Version: 0.3.5
Summary: An application providing access to the Panopto Video Platform SOAP API
Home-page: https://github.com/uw-it-aca/uw-panopto-client
Author: UW-IT T&LS
Author-email: aca-it@uw.edu
License: Apache License, Version 2.0
Classifier: Environment :: Web Environment
Classifier: Framework :: Django
Classifier: Intended Audience :: Developers
Classifier: License :: OSI Approved :: Apache Software License
Classifier: Operating System :: OS Independent
Classifier: Programming Language :: Python
License-File: LICENSE
Requires-Dist: suds ~=1.1
Requires-Dist: commonconf
Requires-Dist: prometheus-client
Requires-Dist: mock
